aihero/__init__.py
aihero/client.py
aihero/exceptions.py
aihero/schema.py
aihero-0.5.1.dist-info/LICENSE
aihero-0.5.1.dist-info/METADATA
aihero-0.5.1.dist-info/WHEEL
aihero-0.5.1.dist-info/entry_points.txt
aihero-0.5.1.dist-info/top_level.txt
aihero-0.5.1.dist-info/RECORD
