Metadata-Version: 2.1
Name: aihero
Version: 0.5.1
Summary: AI Hero Python SDK
Home-page: https://github.com/ai-hero/python-client-sdk
Author: AI Hero Team
Author-email: team@aihero.studio
License: MIT
Keywords: AI Hero,Spotcheck,MLOps,AI,Data Annotation,Labeling,Model Training,Model Serving,Model Deployment
Classifier: License :: OSI Approved :: MIT License
Classifier: Operating System :: OS Independent
Classifier: Programming Language :: Python :: 3 :: Only
Classifier: Programming Language :: Python :: 3.6
Classifier: Programming Language :: Python :: 3.7
Classifier: Programming Language :: Python :: 3.8
Classifier: Programming Language :: Python :: 3.9
Classifier: Programming Language :: Python :: 3.10
Classifier: Programming Language :: Python :: Implementation :: CPython
Classifier: Topic :: Scientific/Engineering :: Artificial Intelligence
Classifier: Topic :: Software Development :: Libraries
License-File: LICENSE
Requires-Dist: httpx
Requires-Dist: python-dotenv
Requires-Dist: validators
Requires-Dist: pydantic
Requires-Dist: names-generator
Requires-Dist: url-normalize
